QUBIT_Driver/CY_10DA.py
QUBIT_Driver/CY_6DA.py
QUBIT_Driver/CY_6DADC.py
QUBIT_Driver/CY_AD.py
QUBIT_Driver/CY_SYNC.py
QUBIT_Driver/__init__.py
qubit_driver-1.1.dist-info/licenses/LICENSE
qubit_driver-1.1.dist-info/METADATA
qubit_driver-1.1.dist-info/WHEEL
qubit_driver-1.1.dist-info/entry_points.txt
qubit_driver-1.1.dist-info/top_level.txt
qubit_driver-1.1.dist-info/RECORD
